<?xml version="1.0"?>

<root>
  <TreeNodesModel>
    <!-- ############################### ACTION NODES ################################# -->

    <Action ID="GoBack"/>

    <Action ID="RmulGoSupply">
      <input_port name="loop_time"></input_port>
      <input_port name="in_supply"></input_port>
      <input_port name="supply_time"></input_port>
    </Action>

    <Action ID="RmulPatrol"/>
   
    <Action ID="SetNavTarget">
      <input_port name="have_target"></input_port>
      <input_port name="gimbal"></input_port>
      <input_port name="target_pos"></input_port>
    </Action>

    <Action ID="SetLeftTarget">
      <input_port name="list"></input_port>
    </Action>

    <Action ID="SetRightTarget">
      <input_port name="list"></input_port>
    </Action>

    <!-- ############################### CONDITION NODES ############################## -->

    <Condition ID="airForce"/>

    <Condition ID="baseUnfolds"/>

    <Condition ID="haveTarget"/>

    <Condition ID="lowHp"/>

    <Condition ID="gameStart"/>

    <Condition ID="outpostSurvives"/>

    <!-- rmul -->
    <Condition ID="rmulCanSupply"/>

    <!-- ############################### CONTROL NODES ################################ -->
    <!-- <Control ID="PipelineSequence"/> -->


    <!-- ############################### DECORATOR NODES ############################## -->
    <!-- <Decorator ID="RateController">
      <input_port name="hz">Rate</input_port>
    </Decorator> -->

  </TreeNodesModel>
</root>
